uuid_by_string/__init__.py
uuid_by_string/uuid_by_string.py
uuid_by_string-0.1.0.dist-info/LICENSE
uuid_by_string-0.1.0.dist-info/METADATA
uuid_by_string-0.1.0.dist-info/WHEEL
uuid_by_string-0.1.0.dist-info/top_level.txt
uuid_by_string-0.1.0.dist-info/RECORD
