Metadata-Version: 2.1
Name: uuid-by-string
Version: 0.1.0
Summary: Generate the RFC-4122 Name-Based UUID.
Home-page: https://github.com/hscspring/uuid-by-string
Author: Yam
Author-email: haoshaochun@gmail.com
License: UNKNOWN
Platform: UNKNOWN
Classifier: Programming Language :: Python :: 3
Classifier: License :: OSI Approved :: Apache Software License
Classifier: Operating System :: OS Independent
